aliyunsdkdysmsapi/__init__.py
aliyunsdkdysmsapi/endpoint.py
aliyunsdkdysmsapi/request/__init__.py
aliyunsdkdysmsapi/request/v20170525/AddShortUrlRequest.py
aliyunsdkdysmsapi/request/v20170525/AddSmsSignRequest.py
aliyunsdkdysmsapi/request/v20170525/AddSmsTemplateRequest.py
aliyunsdkdysmsapi/request/v20170525/DeleteShortUrlRequest.py
aliyunsdkdysmsapi/request/v20170525/DeleteSmsSignRequest.py
aliyunsdkdysmsapi/request/v20170525/DeleteSmsTemplateRequest.py
aliyunsdkdysmsapi/request/v20170525/ListTagResourcesRequest.py
aliyunsdkdysmsapi/request/v20170525/ModifySmsSignRequest.py
aliyunsdkdysmsapi/request/v20170525/ModifySmsTemplateRequest.py
aliyunsdkdysmsapi/request/v20170525/QuerySendDetailsRequest.py
aliyunsdkdysmsapi/request/v20170525/QuerySendStatisticsRequest.py
aliyunsdkdysmsapi/request/v20170525/QueryShortUrlRequest.py
aliyunsdkdysmsapi/request/v20170525/QuerySmsSignListRequest.py
aliyunsdkdysmsapi/request/v20170525/QuerySmsSignRequest.py
aliyunsdkdysmsapi/request/v20170525/QuerySmsTemplateListRequest.py
aliyunsdkdysmsapi/request/v20170525/QuerySmsTemplateRequest.py
aliyunsdkdysmsapi/request/v20170525/SendBatchSmsRequest.py
aliyunsdkdysmsapi/request/v20170525/SendSmsRequest.py
aliyunsdkdysmsapi/request/v20170525/TagResourcesRequest.py
aliyunsdkdysmsapi/request/v20170525/UntagResourcesRequest.py
aliyunsdkdysmsapi/request/v20170525/__init__.py
aliyun_python_sdk_dysmsapi-2.1.2.dist-info/LICENSE
aliyun_python_sdk_dysmsapi-2.1.2.dist-info/METADATA
aliyun_python_sdk_dysmsapi-2.1.2.dist-info/WHEEL
aliyun_python_sdk_dysmsapi-2.1.2.dist-info/top_level.txt
aliyun_python_sdk_dysmsapi-2.1.2.dist-info/RECORD
